README.md
setup.cfg
setup.py
qdi/__init__.py
qdi/py.typed
qdi.egg-info/PKG-INFO
qdi.egg-info/SOURCES.txt
qdi.egg-info/dependency_links.txt
qdi.egg-info/top_level.txt