Metadata-Version: 2.1
Name: qdi
Version: 0.0.1
Summary: Python dependency injection library
Home-page: https://github.com/qooba/python-qdi
Author: Kuba Sołtys
Author-email: dev@qooba.net
License: MIT
Platform: UNKNOWN
Classifier: Development Status :: 3 - Alpha
Classifier: Intended Audience :: Developers
Classifier: License :: OSI Approved :: MIT License
Classifier: Operating System :: OS Independent
Classifier: Programming Language :: Python
Classifier: Programming Language :: Python :: 3.5
Classifier: Programming Language :: Python :: 3.6
Classifier: Programming Language :: Python :: 3.7
Classifier: Topic :: Software Development :: Libraries :: Python Modules
